cashflower-0.10.6.dist-info/RECORD
cashflower-0.10.6.dist-info/LICENSE
cashflower-0.10.6.dist-info/WHEEL
cashflower-0.10.6.dist-info/top_level.txt
cashflower-0.10.6.dist-info/METADATA
cashflower/error.py
cashflower/graph.py
cashflower/__init__.py
cashflower/core.py
cashflower/visualize.py
cashflower/start.py
cashflower/reader.py
cashflower/utils.py
cashflower/cython/discount.pyx
cashflower/cython/__init__.py
cashflower/cython/discount.c
cashflower/cython/discount.cpython-313-darwin.so
cashflower/html_tpl/graph.html
cashflower/model_tpl/run.py
cashflower/model_tpl/model.py
cashflower/model_tpl/input.py
cashflower/model_tpl/settings.py
