Metadata-Version: 2.1
Name: cashflower
Version: 0.10.6
Summary: Framework for actuarial cash flow models
Home-page: https://github.com/acturtle/cashflower
Author: Zuzanna Chmielewska
Project-URL: Source, https://github.com/acturtle/cashflower
Project-URL: Tracker, https://github.com/acturtle/cashflower/issues
Project-URL: Documentation, https://cashflower.acturtle.com
Project-URL: Cheat sheet, https://www.acturtle.com/static/pdf/cheat_sheet.pdf
Requires-Python: >=3.11
License-File: LICENSE
Requires-Dist: pandas
Requires-Dist: psutil
Requires-Dist: networkx
Requires-Dist: numpy
